{
  "blueprint": {
    "name": "AI Boss Holdings Empire",
    "version": "1.0",
    "categories": [
      {
        "name": "FOUNDATION",
        "businesses": [
          {
            "name": "Credit Repair Services",
            "description": "Professional credit repair and optimization services for individuals and businesses",
            "metrics": {
              "automationLevel": "high",
              "startupCost": "low",
              "timeToProfit": "3-6 months"
            },
            "features": [
              "Automated dispute letters",
              "Credit monitoring",
              "Score improvement tracking"
            ],
            "requirements": [],
            "integrations": []
          },
          {
            "name": "Business Credit Building",
            "description": "Help businesses establish and build their credit profiles",
            "metrics": {
              "automationLevel": "medium",
              "startupCost": "low",
              "timeToProfit": "6-12 months"
            },
            "features": [
              "Credit line setup",
              "Vendor programs",
              "Credit monitoring"
            ],
            "requirements": [],
            "integrations": []
          },
          {
            "name": "Personal Branding Agency",
            "description": "Comprehensive personal brand development and management",
            "metrics": {
              "automationLevel": "medium",
              "startupCost": "low",
              "timeToProfit": "immediate"
            },
            "features": [
              "Brand strategy",
              "Social media management",
              "Content creation"
            ],
            "requirements": [],
            "integrations": []
          },
          {
            "name": "Photography Studio",
            "description": "Professional photography services for businesses and individuals",
            "metrics": {
              "automationLevel": "medium",
              "startupCost": "medium",
              "timeToProfit": "3-6 months"
            },
            "features": [
              "Commercial photography",
              "Event coverage",
              "Product shoots"
            ],
            "requirements": [],
            "integrations": []
          },
          {
            "name": "Website Design Agency",
            "description": "Custom website design and development services",
            "metrics": {
              "automationLevel": "high",
              "startupCost": "low",
              "timeToProfit": "immediate"
            },
            "features": [
              "Custom design",
              "E-commerce solutions",
              "SEO optimization"
            ],
            "requirements": [],
            "integrations": []
          },
          {
            "name": "Virtual Mailbox Services",
            "description": "Digital mail management and forwarding services",
            "metrics": {
              "automationLevel": "high",
              "startupCost": "medium",
              "timeToProfit": "6-12 months"
            },
            "features": [
              "Mail scanning",
              "Package forwarding",
              "Digital archiving"
            ],
            "requirements": [],
            "integrations": []
          },
          {
            "name": "Notary & Loan Signing Services",
            "description": "Mobile notary and loan document signing services",
            "metrics": {
              "automationLevel": "low",
              "startupCost": "low",
              "timeToProfit": "immediate"
            },
            "features": [
              "Mobile notary",
              "Loan signing",
              "Document certification"
            ],
            "requirements": [],
            "integrations": []
          },
          {
            "name": "Digital Business Card Platform",
            "description": "Modern digital business card solution",
            "metrics": {
              "automationLevel": "high",
              "startupCost": "low",
              "timeToProfit": "3-6 months"
            },
            "features": [
              "NFC cards",
              "Digital profiles",
              "Analytics"
            ],
            "requirements": [],
            "integrations": []
          },
          {
            "name": "Local SEO & Google My Business Optimization",
            "description": "Local business visibility optimization",
            "metrics": {
              "automationLevel": "high",
              "startupCost": "low",
              "timeToProfit": "3-6 months"
            },
            "features": [
              "GMB optimization",
              "Local citations",
              "Review management"
            ],
            "requirements": [],
            "integrations": []
          },
          {
            "name": "Business Formation Services",
            "description": "Complete business setup and registration services",
            "metrics": {
              "automationLevel": "high",
              "startupCost": "low",
              "timeToProfit": "immediate"
            },
            "features": [
              "LLC formation",
              "Document filing",
              "Compliance support"
            ],
            "requirements": [],
            "integrations": []
          },
          {
            "name": "AI-Powered Resume & LinkedIn Optimization",
            "description": "Career document optimization using AI",
            "metrics": {
              "automationLevel": "high",
              "startupCost": "low",
              "timeToProfit": "immediate"
            },
            "features": [
              "Resume writing",
              "LinkedIn optimization",
              "Career coaching"
            ],
            "requirements": [],
            "integrations": []
          },
          {
            "name": "Automated Bookkeeping & Accounting",
            "description": "AI-powered bookkeeping and accounting services",
            "metrics": {
              "automationLevel": "high",
              "startupCost": "medium",
              "timeToProfit": "3-6 months"
            },
            "features": [
              "Automated reconciliation",
              "Financial reporting",
              "Tax prep"
            ],
            "requirements": [],
            "integrations": []
          },
          {
            "name": "U-Haul Rental Affiliate",
            "description": "U-Haul truck and equipment rental franchise",
            "metrics": {
              "automationLevel": "medium",
              "startupCost": "high",
              "timeToProfit": "6-12 months"
            },
            "features": [
              "Truck rental",
              "Moving supplies",
              "Storage solutions"
            ],
            "requirements": [],
            "integrations": []
          },
          {
            "name": "Vending Machine Business",
            "description": "Smart vending machine network",
            "metrics": {
              "automationLevel": "high",
              "startupCost": "medium",
              "timeToProfit": "6-12 months"
            },
            "features": [
              "Smart machines",
              "Inventory tracking",
              "Mobile payments"
            ],
            "requirements": [],
            "integrations": []
          },
          {
            "name": "Storage Units",
            "description": "Smart self-storage facility network",
            "metrics": {
              "automationLevel": "high",
              "startupCost": "high",
              "timeToProfit": "12+ months"
            },
            "features": [
              "24/7 access",
              "Climate control",
              "Security monitoring"
            ],
            "requirements": [],
            "integrations": []
          },
          {
            "name": "Tax Prep & Filing Services",
            "description": "Professional tax preparation services",
            "metrics": {
              "automationLevel": "high",
              "startupCost": "low",
              "timeToProfit": "immediate"
            },
            "features": [
              "Tax preparation",
              "Electronic filing",
              "Tax planning"
            ],
            "requirements": [],
            "integrations": []
          },
          {
            "name": "Car Rental Fleet",
            "description": "Premium car rental service",
            "metrics": {
              "automationLevel": "high",
              "startupCost": "high",
              "timeToProfit": "12+ months"
            },
            "features": [
              "Luxury vehicles",
              "Mobile app",
              "Contactless rental"
            ],
            "requirements": [],
            "integrations": []
          },
          {
            "name": "Affiliate Marketing Hubs",
            "description": "Network of affiliate marketing websites",
            "metrics": {
              "automationLevel": "high",
              "startupCost": "low",
              "timeToProfit": "6-12 months"
            },
            "features": [
              "Niche websites",
              "Content automation",
              "Affiliate tracking"
            ],
            "requirements": [],
            "integrations": []
          },
          {
            "name": "Monthly Subscription Boxes",
            "description": "Curated subscription box service",
            "metrics": {
              "automationLevel": "medium",
              "startupCost": "medium",
              "timeToProfit": "6-12 months"
            },
            "features": [
              "Curated products",
              "Automated shipping",
              "Member portal"
            ],
            "requirements": [],
            "integrations": []
          },
          {
            "name": "Digital Courses for Small Business Owners",
            "description": "Online business education platform",
            "metrics": {
              "automationLevel": "high",
              "startupCost": "low",
              "timeToProfit": "immediate"
            },
            "features": [
              "Video courses",
              "Resource library",
              "Community access"
            ],
            "requirements": [],
            "integrations": []
          }
        ]
      },
      {
        "name": "INNOVATION",
        "businesses": [
          {
            "name": "AI Automation Agency",
            "description": "End-to-end automation solutions using Make, Sintra, and Zapier",
            "metrics": {
              "automationLevel": "high",
              "startupCost": "low",
              "timeToProfit": "3-6 months"
            },
            "features": [
              "Process automation",
              "Integration development",
              "Workflow optimization"
            ],
            "requirements": [],
            "integrations": []
          },
          {
            "name": "Slack Bot Integration Service",
            "description": "Custom Slack bot development and integration",
            "metrics": {
              "automationLevel": "high",
              "startupCost": "low",
              "timeToProfit": "3-6 months"
            },
            "features": [
              "Custom bot development",
              "Workflow automation",
              "Integration services"
            ],
            "requirements": [],
            "integrations": []
          },
          {
            "name": "SaaS: Lead Gen CRM",
            "description": "Automated lead generation and CRM platform",
            "metrics": {
              "automationLevel": "high",
              "startupCost": "medium",
              "timeToProfit": "6-12 months"
            },
            "features": [
              "Lead scoring",
              "Email automation",
              "Pipeline management"
            ],
            "requirements": [],
            "integrations": []
          },
          {
            "name": "SaaS: Workflow Tracker",
            "description": "Visual workflow and process management tool",
            "metrics": {
              "automationLevel": "high",
              "startupCost": "medium",
              "timeToProfit": "6-12 months"
            },
            "features": [
              "Process mapping",
              "Team collaboration",
              "Analytics"
            ],
            "requirements": [],
            "integrations": []
          },
          {
            "name": "AI Virtual Assistant Marketplace",
            "description": "Platform connecting businesses with AI assistants",
            "metrics": {
              "automationLevel": "high",
              "startupCost": "medium",
              "timeToProfit": "6-12 months"
            },
            "features": [
              "AI matching",
              "Task management",
              "Performance tracking"
            ],
            "requirements": [],
            "integrations": []
          },
          {
            "name": "White-label Chatbot Builder",
            "description": "Custom chatbot development platform",
            "metrics": {
              "automationLevel": "high",
              "startupCost": "medium",
              "timeToProfit": "6-12 months"
            },
            "features": [
              "Visual builder",
              "AI integration",
              "Analytics dashboard"
            ],
            "requirements": [],
            "integrations": []
          },
          {
            "name": "AI Sales Copywriter Tool",
            "description": "AI-powered sales copy generation platform",
            "metrics": {
              "automationLevel": "high",
              "startupCost": "medium",
              "timeToProfit": "3-6 months"
            },
            "features": [
              "Copy generation",
              "A/B testing",
              "Performance analytics"
            ],
            "requirements": [],
            "integrations": []
          },
          {
            "name": "AI-Powered Funnel Builder",
            "description": "Intelligent sales funnel creation platform",
            "metrics": {
              "automationLevel": "high",
              "startupCost": "medium",
              "timeToProfit": "6-12 months"
            },
            "features": [
              "Visual builder",
              "AI optimization",
              "Conversion tracking"
            ],
            "requirements": [],
            "integrations": []
          },
          {
            "name": "Smart Form Builder with Logic",
            "description": "Intelligent form creation platform",
            "metrics": {
              "automationLevel": "high",
              "startupCost": "medium",
              "timeToProfit": "6-12 months"
            },
            "features": [
              "Conditional logic",
              "Integration options",
              "Analytics"
            ],
            "requirements": [],
            "integrations": []
          },
          {
            "name": "Custom Data Dashboards",
            "description": "Business intelligence dashboard platform",
            "metrics": {
              "automationLevel": "high",
              "startupCost": "medium",
              "timeToProfit": "6-12 months"
            },
            "features": [
              "Custom widgets",
              "Data integration",
              "Real-time updates"
            ],
            "requirements": [],
            "integrations": []
          },
          {
            "name": "Voice-to-CRM Transcription Tool",
            "description": "Voice notes to CRM integration platform",
            "metrics": {
              "automationLevel": "high",
              "startupCost": "medium",
              "timeToProfit": "6-12 months"
            },
            "features": [
              "Voice recognition",
              "CRM integration",
              "Mobile app"
            ],
            "requirements": [],
            "integrations": []
          },
          {
            "name": "Event Ticketing Platform",
            "description": "Digital event ticketing solution",
            "metrics": {
              "automationLevel": "high",
              "startupCost": "medium",
              "timeToProfit": "6-12 months"
            },
            "features": [
              "Digital tickets",
              "Event management",
              "Analytics"
            ],
            "requirements": [],
            "integrations": []
          }
        ]
      },
      {
        "name": "RELATIONSHIP",
        "businesses": [
          {
            "name": "Real Estate Investing Firm",
            "description": "Property investment and portfolio management",
            "metrics": {
              "automationLevel": "medium",
              "startupCost": "high",
              "timeToProfit": "12+ months"
            },
            "features": [
              "Property acquisition",
              "Portfolio management",
              "Investment strategy"
            ],
            "requirements": [],
            "integrations": []
          },
          {
            "name": "Property Management Company",
            "description": "Full-service property management solutions",
            "metrics": {
              "automationLevel": "medium",
              "startupCost": "medium",
              "timeToProfit": "6-12 months"
            },
            "features": [
              "Tenant management",
              "Maintenance coordination",
              "Financial reporting"
            ],
            "requirements": [],
            "integrations": []
          },
          {
            "name": "General Contracting Firm",
            "description": "Full-service construction and renovation",
            "metrics": {
              "automationLevel": "low",
              "startupCost": "high",
              "timeToProfit": "6-12 months"
            },
            "features": [
              "Construction",
              "Renovation",
              "Project management"
            ],
            "requirements": [],
            "integrations": []
          },
          {
            "name": "HVAC & Electrical Company",
            "description": "Professional HVAC and electrical services",
            "metrics": {
              "automationLevel": "medium",
              "startupCost": "high",
              "timeToProfit": "3-6 months"
            },
            "features": [
              "HVAC service",
              "Electrical work",
              "24/7 support"
            ],
            "requirements": [],
            "integrations": []
          },
          {
            "name": "Inklyfe Tattoo Shop",
            "description": "Premium tattoo and body art studio",
            "metrics": {
              "automationLevel": "low",
              "startupCost": "medium",
              "timeToProfit": "3-6 months"
            },
            "features": [
              "Custom designs",
              "Professional artists",
              "Sterile environment"
            ],
            "requirements": [],
            "integrations": []
          },
          {
            "name": "Men's Grooming Lounge",
            "description": "Upscale barbershop and grooming services",
            "metrics": {
              "automationLevel": "low",
              "startupCost": "medium",
              "timeToProfit": "immediate"
            },
            "features": [
              "Premium cuts",
              "Grooming services",
              "VIP experience"
            ],
            "requirements": [],
            "integrations": []
          },
          {
            "name": "Mobile Food Truck Fleet",
            "description": "Fleet of gourmet food trucks",
            "metrics": {
              "automationLevel": "medium",
              "startupCost": "high",
              "timeToProfit": "6-12 months"
            },
            "features": [
              "Gourmet menu",
              "Event catering",
              "Location tracking"
            ],
            "requirements": [],
            "integrations": []
          },
          {
            "name": "Community Outreach Nonprofit",
            "description": "Worldwide Giving Network for community support",
            "metrics": {
              "automationLevel": "medium",
              "startupCost": "low",
              "timeToProfit": "12+ months"
            },
            "features": [
              "Community programs",
              "Donation management",
              "Impact tracking"
            ],
            "requirements": [],
            "integrations": []
          },
          {
            "name": "Private Membership Club",
            "description": "Exclusive networking and lifestyle club",
            "metrics": {
              "automationLevel": "medium",
              "startupCost": "high",
              "timeToProfit": "12+ months"
            },
            "features": [
              "Exclusive events",
              "Networking",
              "Concierge service"
            ],
            "requirements": [],
            "integrations": []
          },
          {
            "name": "Podcast Network",
            "description": "Network of business and lifestyle podcasts",
            "metrics": {
              "automationLevel": "medium",
              "startupCost": "medium",
              "timeToProfit": "6-12 months"
            },
            "features": [
              "Original content",
              "Advertising",
              "Distribution"
            ],
            "requirements": [],
            "integrations": []
          },
          {
            "name": "Personal Coaching Services",
            "description": "Professional life and business coaching",
            "metrics": {
              "automationLevel": "medium",
              "startupCost": "low",
              "timeToProfit": "immediate"
            },
            "features": [
              "1-on-1 coaching",
              "Group programs",
              "Online courses"
            ],
            "requirements": [],
            "integrations": []
          },
          {
            "name": "Networking Event Brand",
            "description": "High-end business networking events",
            "metrics": {
              "automationLevel": "medium",
              "startupCost": "medium",
              "timeToProfit": "3-6 months"
            },
            "features": [
              "Exclusive venues",
              "Speaker series",
              "Member networking"
            ],
            "requirements": [],
            "integrations": []
          }
        ]
      },
      {
        "name": "KNOWLEDGE",
        "businesses": [
          {
            "name": "Angels in Daylight Fashion Brand",
            "description": "Premium fashion brand with cultural significance",
            "metrics": {
              "automationLevel": "medium",
              "startupCost": "high",
              "timeToProfit": "12+ months"
            },
            "features": [
              "Fashion design",
              "E-commerce",
              "Brand storytelling"
            ],
            "requirements": [],
            "integrations": []
          },
          {
            "name": "Merch Brand for Ai Boss Holdings",
            "description": "Official merchandise for the AI Boss Holdings ecosystem",
            "metrics": {
              "automationLevel": "high",
              "startupCost": "medium",
              "timeToProfit": "3-6 months"
            },
            "features": [
              "Branded apparel",
              "Accessories",
              "Print on demand"
            ],
            "requirements": [],
            "integrations": []
          },
          {
            "name": "Children's Clothing Line",
            "description": "Angels in Daylight sub-brand for children",
            "metrics": {
              "automationLevel": "medium",
              "startupCost": "high",
              "timeToProfit": "12+ months"
            },
            "features": [
              "Kids fashion",
              "Sustainable materials",
              "Educational elements"
            ],
            "requirements": [],
            "integrations": []
          },
          {
            "name": "Digital Academy",
            "description": "Business automation education platform",
            "metrics": {
              "automationLevel": "high",
              "startupCost": "medium",
              "timeToProfit": "3-6 months"
            },
            "features": [
              "Online courses",
              "Live workshops",
              "Community support"
            ],
            "requirements": [],
            "integrations": []
          },
          {
            "name": "Make.com & Sintra AI Certification Course",
            "description": "Professional automation tool certification",
            "metrics": {
              "automationLevel": "high",
              "startupCost": "low",
              "timeToProfit": "immediate"
            },
            "features": [
              "Video courses",
              "Hands-on projects",
              "Certification exam"
            ],
            "requirements": [],
            "integrations": []
          },
          {
            "name": "E-learning Platform for Credit & Financial Literacy",
            "description": "Comprehensive financial education platform",
            "metrics": {
              "automationLevel": "high",
              "startupCost": "medium",
              "timeToProfit": "3-6 months"
            },
            "features": [
              "Interactive courses",
              "Financial tools",
              "Community support"
            ],
            "requirements": [],
            "integrations": []
          },
          {
            "name": "Youth Entrepreneurship Curriculum",
            "description": "Entrepreneurship education for young people",
            "metrics": {
              "automationLevel": "medium",
              "startupCost": "low",
              "timeToProfit": "6-12 months"
            },
            "features": [
              "Interactive lessons",
              "Mentorship",
              "Project-based learning"
            ],
            "requirements": [],
            "integrations": []
          },
          {
            "name": "Home-schooling Content for Fathers & Sons",
            "description": "Specialized homeschooling curriculum",
            "metrics": {
              "automationLevel": "medium",
              "startupCost": "low",
              "timeToProfit": "6-12 months"
            },
            "features": [
              "Custom curriculum",
              "Activity guides",
              "Progress tracking"
            ],
            "requirements": [],
            "integrations": []
          },
          {
            "name": "AI-Powered Tutoring Platform",
            "description": "Personalized AI tutoring service",
            "metrics": {
              "automationLevel": "high",
              "startupCost": "medium",
              "timeToProfit": "6-12 months"
            },
            "features": [
              "AI tutors",
              "Adaptive learning",
              "Progress tracking"
            ],
            "requirements": [],
            "integrations": []
          },
          {
            "name": "Branding & Design Templates Marketplace",
            "description": "Premium design template platform",
            "metrics": {
              "automationLevel": "high",
              "startupCost": "low",
              "timeToProfit": "3-6 months"
            },
            "features": [
              "Premium templates",
              "Custom branding",
              "Design tools"
            ],
            "requirements": [],
            "integrations": []
          },
          {
            "name": "Voiceover + AI Script Library",
            "description": "AI-powered voiceover and script platform",
            "metrics": {
              "automationLevel": "high",
              "startupCost": "medium",
              "timeToProfit": "6-12 months"
            },
            "features": [
              "AI voices",
              "Script templates",
              "Custom voices"
            ],
            "requirements": [],
            "integrations": []
          },
          {
            "name": "Real Estate Licensing Prep Course",
            "description": "Real estate exam preparation platform",
            "metrics": {
              "automationLevel": "high",
              "startupCost": "low",
              "timeToProfit": "3-6 months"
            },
            "features": [
              "Study materials",
              "Practice exams",
              "Coaching"
            ],
            "requirements": [],
            "integrations": []
          },
          {
            "name": "Trade Skills Bootcamp",
            "description": "Hands-on trade skills training program",
            "metrics": {
              "automationLevel": "low",
              "startupCost": "high",
              "timeToProfit": "6-12 months"
            },
            "features": [
              "Practical training",
              "Certification prep",
              "Job placement"
            ],
            "requirements": [],
            "integrations": []
          }
        ]
      }
    ]
  }
}